nyquisis/__init__.py
nyquisis/nyquisis.py
Nyquisis-1.0.3.dist-info/LICENSE
Nyquisis-1.0.3.dist-info/METADATA
Nyquisis-1.0.3.dist-info/WHEEL
Nyquisis-1.0.3.dist-info/entry_points.txt
Nyquisis-1.0.3.dist-info/top_level.txt
Nyquisis-1.0.3.dist-info/RECORD
