Metadata-Version: 2.1
Name: Nyquisis
Version: 1.0.3
Summary: A simple tool automatically drops the duplicate pages in PDF files.
Home-page: https://github.com/Enoch2090/Nyquisis
Author: Enoch2090
Author-email: gyc990926@gmail.com
License: GPLv3
Keywords: Nyquisis
Platform: any
Classifier: Programming Language :: Python
Classifier: Programming Language :: Python :: 3
Classifier: Programming Language :: Python :: 3.7
Classifier: Programming Language :: Python :: 3.8
Classifier: Operating System :: OS Independent
Requires-Python: >=3.7
License-File: LICENSE
